tipranks/__init__.py
tipranks/base.py
tipranks/errors.py
tipranks-0.0.7.dist-info/LICENSE
tipranks-0.0.7.dist-info/METADATA
tipranks-0.0.7.dist-info/WHEEL
tipranks-0.0.7.dist-info/top_level.txt
tipranks-0.0.7.dist-info/RECORD
