Metadata-Version: 2.1
Name: tipranks
Version: 0.0.7
Summary: Python interface to communicate with TipRanks API.
Home-page: UNKNOWN
Author: visuxls
License: UNKNOWN
Platform: UNKNOWN
Classifier: Programming Language :: Python :: 3
Classifier: License :: OSI Approved :: MIT License
Classifier: Operating System :: OS Independent
Requires-Python: >=3.6
Requires-Dist: requests
